datasette_acl/__init__.py
datasette_acl/hookspecs.py
datasette_acl/utils.py
datasette_acl/static/Choices.js.LICENSE
datasette_acl/static/choices-9.0.1.min.css
datasette_acl/static/choices-9.0.1.min.js
datasette_acl/templates/manage_acl_group.html
datasette_acl/templates/manage_acl_groups.html
datasette_acl/templates/manage_table_acls.html
datasette_acl/views/__init__.py
datasette_acl/views/groups.py
datasette_acl/views/table_acls.py
datasette_acl-0.5a0.dist-info/licenses/LICENSE
datasette_acl-0.5a0.dist-info/METADATA
datasette_acl-0.5a0.dist-info/WHEEL
datasette_acl-0.5a0.dist-info/entry_points.txt
datasette_acl-0.5a0.dist-info/top_level.txt
datasette_acl-0.5a0.dist-info/RECORD
