Metadata-Version: 2.4
Name: datasette-acl
Version: 0.5a0
Summary: Advanced permission management for Datasette
Author: Simon Willison
License-Expression: Apache-2.0
Project-URL: Homepage, https://github.com/datasette/datasette-acl
Project-URL: Changelog, https://github.com/datasette/datasette-acl/releases
Project-URL: Issues, https://github.com/datasette/datasette-acl/issues
Project-URL: CI, https://github.com/datasette/datasette-acl/actions
Classifier: Framework :: Datasette
Requires-Python: >=3.10
License-File: LICENSE
Requires-Dist: datasette>=1.0a20
Provides-Extra: test
Requires-Dist: pytest; extra == "test"
Requires-Dist: pytest-asyncio; extra == "test"
Dynamic: license-file
